sonusai_asr_faster_whisper/__init__.py
sonusai_asr_faster_whisper/asr_functions/__init__.py
sonusai_asr_faster_whisper/asr_functions/faster_whisper.py
sonusai_asr_faster_whisper-0.2.0.dist-info/METADATA
sonusai_asr_faster_whisper-0.2.0.dist-info/WHEEL
sonusai_asr_faster_whisper-0.2.0.dist-info/RECORD
